{
    "document_type": "comparison",
    "file_path": "C:/Users/tonig/PythonProjects/text-annotation-tool/data/comparison/3.json",
    "file_name": "3",
    "meta_tags": {},
    "text": "a.\n\n1.\n\nc.\n\nd.\n\ne.\n\nf.\n\ng.\n\nh.\n\ni.\n\nj.\n\nk.\n\nl.\n\nm.\n\nn.\n\no.\n\np.\n\nq.\n\nr.\n\ns.\n\nt.\n\nu.\n\nv.\n\nw.\n\nx.\n\ny.\n\nz.\n\naa.\n\nba.\n\nca.\n\nda.\n\nea.\n\nfa.\n\nga.\n\nha.\n\nia.\n\nja.\n\nka.\n\nla.\n\nma.\n\nna.\n\noa.\n\npa.\n\nqa.\n\nra.\n\nsa.\n\nta.\n\nua.\n\nva.\n\nwa.\n\nxa.\n\nya.\n\nza.\n\nab.\n\nbb.\n\ncb.\n\ndb.\n\neb.\n\nfb.\n\ngb.\n\nhb.\n\nib.\n\njb.\n\nkb.\n\nlb.\n\nmb.\n\nnb.\n\nob.\n\npb.\n\nqb.\n\nrb.\n\nsb.\n\ntb.\n\nub.\n\nvb.\n\nwb.\n\nxb.\n\nzb.\n\n"
}